judge_pics/__init__.py
judge_pics/search.py
judge_pics/update.py
judge_pics/upload.py
judge_pics/data/people.json
judge_pics/scrapers/__init__.py
judge_pics/scrapers/cand_judges.py
judge_pics/scrapers/dc_circuit_judges.py
judge_pics-2.0.5.dist-info/LICENSE
judge_pics-2.0.5.dist-info/METADATA
judge_pics-2.0.5.dist-info/WHEEL
judge_pics-2.0.5.dist-info/top_level.txt
judge_pics-2.0.5.dist-info/RECORD
