Metadata-Version: 2.1
Name: judge-pics
Version: 2.0.5
Summary: Database of Judge Pictures
Author: Mike Lissner
Author-email: info@free.law
Maintainer: Mike Lisser
Maintainer-email: info@free.law
Classifier: Development Status :: 5 - Production/Stable
Classifier: Intended Audience :: Developers
Classifier: Natural Language :: English
Classifier: License :: OSI Approved :: BSD License
Classifier: Operating System :: OS Independent
Classifier: Programming Language :: Python
Classifier: Programming Language :: Python :: 3
Classifier: Programming Language :: Python :: 3.7
Classifier: Programming Language :: Python :: 3.8
Classifier: Programming Language :: Python :: 3.9
Classifier: Programming Language :: Python :: 3.10
Classifier: Programming Language :: Python :: 3.11
Classifier: Programming Language :: Python :: 3.12
Classifier: Programming Language :: Python :: Implementation :: CPython
Classifier: Programming Language :: Python :: Implementation :: PyPy
Classifier: Topic :: Software Development :: Libraries :: Python Modules
License-File: LICENSE
Requires-Dist: python-dateutil >=2.0
Requires-Dist: lxml >=4.0
Requires-Dist: requests >=2.0
Requires-Dist: climage
Requires-Dist: python-Levenshtein
Requires-Dist: fuzzywuzzy
Requires-Dist: setuptools
